HISTORY.txt
LICENSE.txt
MANIFEST.in
README.rst
setup.py
diazotheme/__init__.py
diazotheme.bootstrap.egg-info/PKG-INFO
diazotheme.bootstrap.egg-info/SOURCES.txt
diazotheme.bootstrap.egg-info/dependency_links.txt
diazotheme.bootstrap.egg-info/entry_points.txt
diazotheme.bootstrap.egg-info/namespace_packages.txt
diazotheme.bootstrap.egg-info/not-zip-safe
diazotheme.bootstrap.egg-info/requires.txt
diazotheme.bootstrap.egg-info/top_level.txt
diazotheme/bootstrap/__init__.py
diazotheme/bootstrap/configure.zcml
diazotheme/bootstrap/portlet/__init__.py
diazotheme/bootstrap/portlet/carousel.pt
diazotheme/bootstrap/portlet/carousel.py
diazotheme/bootstrap/portlet/configure.zcml
diazotheme/bootstrap/profiles/default/cssregistry.xml
diazotheme/bootstrap/profiles/default/metadata.xml
diazotheme/bootstrap/profiles/default/portlets.xml
diazotheme/bootstrap/profiles/default/theme.xml
diazotheme/bootstrap/static/404.html
diazotheme/bootstrap/static/apple-touch-icon-114x114-precomposed.png
diazotheme/bootstrap/static/apple-touch-icon-57x57-precomposed.png
diazotheme/bootstrap/static/apple-touch-icon-72x72-precomposed.png
diazotheme/bootstrap/static/apple-touch-icon-precomposed.png
diazotheme/bootstrap/static/apple-touch-icon.png
diazotheme/bootstrap/static/base.html
diazotheme/bootstrap/static/crossdomain.xml
diazotheme/bootstrap/static/dialog.html
diazotheme/bootstrap/static/facetednavigation-rules.xml
diazotheme/bootstrap/static/favicon.ico
diazotheme/bootstrap/static/htmltidy.pl
diazotheme/bootstrap/static/humans.txt
diazotheme/bootstrap/static/jquery-1.7.1.min.js
diazotheme/bootstrap/static/manifest.cfg
diazotheme/bootstrap/static/navigation-rules.xml
diazotheme/bootstrap/static/portlet-rules.xml
diazotheme/bootstrap/static/robots.txt
diazotheme/bootstrap/static/rules.xml
diazotheme/bootstrap/static/bootstrap/css/bootstrap-responsive.css
diazotheme/bootstrap/static/bootstrap/css/bootstrap-responsive.min.css
diazotheme/bootstrap/static/bootstrap/css/bootstrap.css
diazotheme/bootstrap/static/bootstrap/css/bootstrap.min.css
diazotheme/bootstrap/static/bootstrap/img/glyphicons-halflings-white.png
diazotheme/bootstrap/static/bootstrap/img/glyphicons-halflings.png
diazotheme/bootstrap/static/bootstrap/js/bootstrap.js
diazotheme/bootstrap/static/bootstrap/js/bootstrap.min.js
diazotheme/bootstrap/static/css/editview.css
