Metadata-Version: 1.1
Name: diazotheme.bootstrap
Version: 0.3
Summary: Plone theme based on Twitter's Bootstrap CSS
Home-page: https://github.com/kagesenshi/diazotheme.bootstrap
Author: Izhar Firdaus
Author-email: izhar@inigo-tech.com
License: Apache License 2.0
Keywords: plone diazo theme
Platform: UNKNOWN
Classifier: Programming Language :: Python
